scabha/__init__.py
scabha/basetypes.py
scabha/cab_utils.py
scabha/cargo.py
scabha/configuratt/__init__.py
scabha/configuratt/cache.py
scabha/configuratt/common.py
scabha/configuratt/deps.py
scabha/configuratt/resolvers.py
scabha/evaluator.py
scabha/exceptions.py
scabha/logging_utils.py
scabha/proc_utils.py
scabha/schema_utils.py
scabha/substitutions.py
scabha/validate.py
stimela/__init__.py
stimela/backends/__init__.py
stimela/backends/docker.py
stimela/backends/flavours/__init__.py
stimela/backends/flavours/binary.py
stimela/backends/flavours/casa.py
stimela/backends/flavours/python_flavours.py
stimela/backends/kube/__init__.py
stimela/backends/kube/daskjob.py
stimela/backends/kube/infrastructure.py
stimela/backends/kube/kube_utils.py
stimela/backends/kube/pod_proxy.py
stimela/backends/kube/run_daskjob.py
stimela/backends/kube/run_kube.py
stimela/backends/native/__init__.py
stimela/backends/native/run_native.py
stimela/backends/podman.py
stimela/backends/runner.py
stimela/backends/singularity.py
stimela/backends/slurm.py
stimela/backends/utils.py
stimela/cargo/__init__.py
stimela/commands/__init__.py
stimela/commands/build.py
stimela/commands/cabs.py
stimela/commands/cleanup.py
stimela/commands/containers.py
stimela/commands/doc.py
stimela/commands/images.py
stimela/commands/kill.py
stimela/commands/ps.py
stimela/commands/pull.py
stimela/commands/push.py
stimela/commands/run.py
stimela/commands/save_config.py
stimela/config.py
stimela/exceptions.py
stimela/kitchen/__init__.py
stimela/kitchen/batch.py
stimela/kitchen/cab.py
stimela/kitchen/recipe.py
stimela/kitchen/step.py
stimela/kitchen/utils.py
stimela/kitchen/wranglers.py
stimela/main.py
stimela/schedulers/__init__.py
stimela/schedulers/slurm.py
stimela/stimela.conf
stimela/stimelogging.py
stimela/task_stats.py
stimela/utils/__init__.py
stimela/utils/xrun_asyncio.py
stimela/utils/xrun_poll.py
scabha_tests/__init__.py
scabha_tests/test_clickify.py
scabha_tests/test_clickify.yaml
scabha_tests/test_configuratt.py
stimela-2.1.3.dist-info/LICENSE
stimela-2.1.3.dist-info/METADATA
stimela-2.1.3.dist-info/WHEEL
stimela-2.1.3.dist-info/entry_points.txt
stimela-2.1.3.dist-info/RECORD
